Metadata-Version: 2.1
Name: ENATool
Version: 0.0.0
Summary: Convenient dowloader of raw files from ENA
Home-page: https://github.com/RCPCM-GCB/ENA_tool
Author: P.Tikhonova
Author-email: tikhonova.polly@mail.ru
License: MIT
Platform: UNKNOWN
